win32_show/__init__.py
win32_show/main.py
win32_show-0.1.0.dist-info/LICENSE
win32_show-0.1.0.dist-info/METADATA
win32_show-0.1.0.dist-info/WHEEL
win32_show-0.1.0.dist-info/entry_points.txt
win32_show-0.1.0.dist-info/top_level.txt
win32_show-0.1.0.dist-info/RECORD
